{"id": 51973, "qid": 51973, "publicid": 51973, "orgid": 0, "levelname": "3D+", "min_levelname": "", "max_levelname": "", "qtype": 5, "qtypename": "\u5b98\u5b50\u9898", "status": 2, "userid": 14637, "username": "273312617", "hasdia": true, "dias": [], "attr_type": 0, "layoutnumber": 1, "issingle": true, "enable_answer": true, "sms_count": 1, "edit_count": 0, "islei": false, "leiid": 0, "taotaiid": 0, "bookinfos": [{"bookname": "\u5b98\u5b50\u7684\u624b\u7b4b\u3000\u65e5\u672c\u3000\u5742\u7530\u8363\u7537", "bookid": 894, "pinyin": "", "nodename": "\u7b2c\u4e00\u7ae0\u3000\u5927\u5b98\u5b50\u7684\u5927\u6280\u300024\u9898", "bookurl": 894}, {"bookname": "\u300a\u94f6\u5188\u68cb\u9662\u5b98\u5b50\u624b\u7b4b\u4e60\u9898\u96c6\u300b", "bookid": 3659, "pinyin": "", "nodename": "\u5742\u7530\u8363\u7537\u5b98\u5b50\u624b\u7b4b", "bookurl": 3659}], "specs": [], "taskresult": {"ok_nums": [2, 2, 1, 1, 2, 1, 1, 2, 2, 3, 2, 3, 3, 8, 9, 7, 9, 11, 14, 22, 20, 38, 42, 71, 46, 63, 58, 32, 35, 38], "fail_nums": [10, 3, 4, 1, 0, 5, 2, 7, 6, 3, 10, 15, 14, 11, 16, 22, 18, 21, 23, 31, 34, 80, 48, 77, 94, 75, 58, 27, 15, 19], "ok_total": 548, "fail_total": 749}, "xuandians": [], "xds": [], "options": [], "vote": 4.8, "name": "", "title": "", "c": "amsTVUIRHRATVUMRHRATVkMRHRATW0IRHRATV1wRHRATV10RHRATUF0RHRATVV0RHRATUEMRHRATVkERbBwRaBFXQBIdExFXQRIdExFWQBIdExFQXhIdExFRXhIdExFRXxIdExFRXBIdExFQWxIdExFXQxJsbg==", "r": 2, "prepos": [["qf", "pf", "pe", "qh", "od"], ["qd", "pd", "qe"]], "xv": 4, "points": [], "lu": 19, "blackfirst": true, "is_share": true, "answers": [{"id": 241749, "st": 2, "ty": 1, "nu": 1, "username": "273312617", "userid": 14784, "pts": [{"p": "rc", "c": ""}, {"p": "qc", "c": ""}, {"p": "qb", "c": ""}, {"p": "pb", "c": ""}, {"p": "sd", "c": ""}, {"p": "pc", "c": ""}, {"p": "ra", "c": "\u606d\u559c\u7b54\u5bf9"}], "v": 0, "ok_count": 2, "change_count": 0, "bad_count": 0, "error_count": 1, "created": 1437213101}, {"id": 1812491, "st": 1, "ty": 1, "nu": 19, "username": "\u76ae\u5361\u4e18\u54df", "userid": 791665, "pts": [{"p": "rc", "c": ""}, {"p": "qc", "c": ""}, {"p": "qb", "c": ""}, {"p": "sd", "c": ""}, {"p": "pb", "c": ""}, {"p": "rf", "c": ""}, {"p": "rb", "c": ""}, {"p": "pa", "c": ""}, {"p": "rg", "c": ""}, {"p": "se", "c": ""}, {"p": "sg", "c": ""}], "v": 0, "ok_count": 1, "change_count": 0, "bad_count": 0, "error_count": 0, "created": 1657796737}, {"id": 2263764, "st": 1, "ty": 1, "nu": 21, "username": "w_22718418194221", "userid": 1546007, "pts": [{"p": "rc", "c": ""}, {"p": "qc", "c": ""}, {"p": "qb", "c": ""}, {"p": "pb", "c": ""}, {"p": "sd", "c": ""}, {"p": "pc", "c": ""}, {"p": "ra", "c": ""}, {"p": "rf", "c": ""}, {"p": "se", "c": ""}, {"p": "sf", "c": ""}, {"p": "sc", "c": ""}], "v": 0, "ok_count": 1, "change_count": 0, "bad_count": 0, "error_count": 0, "created": 1704799986}, {"id": 241968, "st": 2, "ty": 2, "nu": 2, "username": "273312617", "userid": 14784, "pts": [{"p": "rc", "c": ""}, {"p": "rf", "c": ""}, {"p": "qc", "c": ""}, {"p": "se", "c": ""}, {"p": "sc", "c": ""}, {"p": "sd", "c": ""}, {"p": "sg", "c": ""}], "v": 0, "ok_count": 0, "change_count": 10, "bad_count": 0, "error_count": 0, "created": 1437268175}, {"id": 241970, "st": 2, "ty": 2, "nu": 4, "username": "273312617", "userid": 14784, "pts": [{"p": "rc", "c": ""}, {"p": "qc", "c": ""}, {"p": "qb", "c": ""}, {"p": "sd", "c": ""}, {"p": "pb", "c": ""}, {"p": "rb", "c": ""}, {"p": "sb", "c": ""}, {"p": "sc", "c": ""}, {"p": "ra", "c": ""}], "v": 0, "ok_count": 1, "change_count": 10, "bad_count": 0, "error_count": 1, "created": 1437268281}, {"id": 388660, "st": 1, "ty": 2, "nu": 6, "username": "\u9b54\u672f\u732b", "userid": 20687, "pts": [{"p": "rc", "c": ""}, {"p": "qc", "c": ""}, {"p": "qb", "c": ""}, {"p": "sd", "c": ""}, {"p": "pb", "c": ""}, {"p": "rb", "c": ""}, {"p": "sb", "c": ""}, {"p": "sc", "c": ""}, {"p": "ra", "c": ""}, {"p": "sa", "c": ""}], "v": 0, "ok_count": 0, "change_count": 1, "bad_count": 0, "error_count": 0, "created": 1463568255}, {"id": 403560, "st": 1, "ty": 2, "nu": 7, "username": "\u674e\u6625\u5b87", "userid": 28327, "pts": [{"p": "rc", "c": ""}, {"p": "qc", "c": ""}, {"p": "qb", "c": ""}, {"p": "pb", "c": ""}, {"p": "sd", "c": ""}, {"p": "pc", "c": ""}, {"p": "rb", "c": ""}], "v": 0, "ok_count": 6, "change_count": 2, "bad_count": 0, "error_count": 1, "created": 1468299449}, {"id": 408237, "st": 1, "ty": 2, "nu": 10, "username": "welson", "userid": 36817, "pts": [{"p": "rc", "c": ""}, {"p": "qc", "c": ""}, {"p": "qb", "c": ""}, {"p": "sd", "c": ""}, {"p": "pb", "c": ""}, {"p": "rb", "c": ""}, {"p": "sb", "c": ""}, {"p": "sc", "c": ""}, {"p": "ra", "c": ""}, {"p": "rf", "c": ""}, {"p": "rc", "c": ""}, {"p": "se", "c": ""}, {"p": "pa", "c": ""}, {"p": "rb", "c": ""}], "v": 0, "ok_count": 0, "change_count": 1, "bad_count": 1, "error_count": 0, "created": 1470229550}, {"id": 693620, "st": 1, "ty": 2, "nu": 12, "username": "phillip99", "userid": 2091, "pts": [{"p": "rc", "c": ""}, {"p": "qc", "c": ""}, {"p": "qb", "c": ""}, {"p": "sd", "c": ""}, {"p": "pb", "c": ""}, {"p": "rf", "c": ""}, {"p": "rb", "c": ""}, {"p": "rg", "c": ""}, {"p": "sc", "c": ""}, {"p": "se", "c": ""}, {"p": "sa", "c": ""}], "v": 0, "ok_count": 0, "change_count": 2, "bad_count": 0, "error_count": 0, "created": 1539489591}, {"id": 693621, "st": 1, "ty": 2, "nu": 13, "username": "phillip99", "userid": 2091, "pts": [{"p": "rc", "c": ""}, {"p": "qc", "c": ""}, {"p": "qb", "c": ""}, {"p": "sd", "c": ""}, {"p": "pb", "c": ""}, {"p": "rf", "c": ""}, {"p": "rb", "c": ""}, {"p": "pa", "c": ""}, {"p": "rg", "c": ""}, {"p": "se", "c": ""}, {"p": "sg", "c": ""}, {"p": "qa", "c": ""}, {"p": "sf", "c": ""}, {"p": "ra", "c": ""}, {"p": "re", "c": ""}], "v": 0, "ok_count": 0, "change_count": 2, "bad_count": 0, "error_count": 0, "created": 1539489609}, {"id": 1828112, "st": 1, "ty": 2, "nu": 20, "username": "\u9648\u5609\u660e21", "userid": 1218322, "pts": [{"p": "rc", "c": ""}, {"p": "qc", "c": ""}, {"p": "qb", "c": ""}, {"p": "sd", "c": ""}, {"p": "pb", "c": ""}, {"p": "rf", "c": ""}, {"p": "ra", "c": ""}, {"p": "rg", "c": ""}, {"p": "sc", "c": ""}, {"p": "se", "c": ""}, {"p": "pa", "c": ""}], "v": 0, "ok_count": 0, "change_count": 1, "bad_count": 0, "error_count": 0, "created": 1659054463}, {"id": 2966106, "st": 1, "ty": 2, "nu": 24, "username": "g_567503195310", "userid": 2419488, "pts": [{"p": "rc", "c": ""}, {"p": "qc", "c": ""}, {"p": "qb", "c": ""}, {"p": "pb", "c": ""}, {"p": "sd", "c": ""}, {"p": "pc", "c": ""}, {"p": "rb", "c": ""}, {"p": "rf", "c": ""}, {"p": "se", "c": ""}], "v": 0, "ok_count": 0, "change_count": 1, "bad_count": 0, "error_count": 0, "created": 1764855443}, {"id": 241969, "st": 2, "ty": 3, "nu": 3, "username": "273312617", "userid": 14784, "pts": [{"p": "rc", "c": ""}, {"p": "qc", "c": ""}, {"p": "sd", "c": ""}, {"p": "qb", "c": ""}], "v": 0, "ok_count": 0, "change_count": 0, "bad_count": 10, "error_count": 0, "created": 1437268227}, {"id": 241971, "st": 2, "ty": 3, "nu": 5, "username": "273312617", "userid": 14784, "pts": [{"p": "qb", "c": ""}, {"p": "rc", "c": ""}, {"p": "rb", "c": ""}, {"p": "rf", "c": ""}, {"p": "sb", "c": ""}, {"p": "rg", "c": ""}, {"p": "sd", "c": ""}, {"p": "se", "c": ""}, {"p": "sc", "c": ""}, {"p": "rh", "c": ""}], "v": 0, "ok_count": 0, "change_count": 0, "bad_count": 10, "error_count": 0, "created": 1437268347}, {"id": 407775, "st": 1, "ty": 3, "nu": 8, "username": "welson", "userid": 36817, "pts": [{"p": "rc", "c": ""}, {"p": "qc", "c": ""}, {"p": "qb", "c": ""}, {"p": "pb", "c": ""}, {"p": "sd", "c": ""}, {"p": "pc", "c": ""}, {"p": "rb", "c": ""}, {"p": "qa", "c": ""}, {"p": "rf", "c": ""}, {"p": "ra", "c": ""}, {"p": "sc", "c": "\u640d4\u76ee"}], "v": 0, "ok_count": 0, "change_count": 0, "bad_count": 1, "error_count": 0, "created": 1470042529}, {"id": 407777, "st": 1, "ty": 3, "nu": 9, "username": "welson", "userid": 36817, "pts": [{"p": "rc", "c": ""}, {"p": "qc", "c": ""}, {"p": "qb", "c": ""}, {"p": "pb", "c": ""}, {"p": "sd", "c": ""}, {"p": "pc", "c": ""}, {"p": "rb", "c": ""}, {"p": "qa", "c": ""}, {"p": "ra", "c": ""}, {"p": "rf", "c": ""}, {"p": "se", "c": ""}, {"p": "sc", "c": ""}, {"p": "sb", "c": ""}, {"p": "sf", "c": "\u5168\u6b7b"}], "v": 0, "ok_count": 0, "change_count": 0, "bad_count": 2, "error_count": 0, "created": 1470042546}, {"id": 690489, "st": 1, "ty": 3, "nu": 11, "username": "\u51af\u65fb\u704f", "userid": 208247, "pts": [{"p": "rc", "c": ""}, {"p": "qc", "c": ""}, {"p": "qb", "c": ""}, {"p": "sd", "c": ""}, {"p": "se", "c": ""}, {"p": "pb", "c": ""}, {"p": "sc", "c": ""}, {"p": "pc", "c": ""}], "v": 0, "ok_count": 0, "change_count": 0, "bad_count": 2, "error_count": 1, "created": 1538825603}, {"id": 699315, "st": 1, "ty": 3, "nu": 14, "username": "\u5feb\u4e50\u5c0f\u7b1b\u5b50", "userid": 92390, "pts": [{"p": "rc", "c": ""}, {"p": "qc", "c": ""}, {"p": "qb", "c": ""}, {"p": "pb", "c": ""}, {"p": "sd", "c": ""}, {"p": "pc", "c": ""}, {"p": "rb", "c": ""}, {"p": "qa", "c": ""}, {"p": "rf", "c": ""}, {"p": "ra", "c": ""}], "v": 0, "ok_count": 0, "change_count": 0, "bad_count": 1, "error_count": 0, "created": 1540696233}, {"id": 699316, "st": 1, "ty": 3, "nu": 15, "username": "\u5feb\u4e50\u5c0f\u7b1b\u5b50", "userid": 92390, "pts": [{"p": "rc", "c": ""}, {"p": "qc", "c": ""}, {"p": "qb", "c": ""}, {"p": "pb", "c": ""}, {"p": "sd", "c": ""}, {"p": "pc", "c": ""}, {"p": "rb", "c": ""}, {"p": "qa", "c": ""}, {"p": "ra", "c": ""}, {"p": "rf", "c": ""}, {"p": "se", "c": ""}, {"p": "sc", "c": ""}], "v": 0, "ok_count": 0, "change_count": 0, "bad_count": 1, "error_count": 0, "created": 1540696245}, {"id": 721211, "st": 1, "ty": 3, "nu": 16, "username": "\u7530\u6c90\u6c90", "userid": 222874, "pts": [{"p": "rc", "c": ""}, {"p": "qc", "c": ""}, {"p": "qb", "c": ""}, {"p": "sd", "c": ""}, {"p": "pb", "c": ""}, {"p": "rf", "c": ""}, {"p": "rb", "c": ""}], "v": 0, "ok_count": 0, "change_count": 0, "bad_count": 1, "error_count": 0, "created": 1545314429}, {"id": 814307, "st": 1, "ty": 3, "nu": 17, "username": "\u6211\u7231\u5b66\u56f4\u68cb", "userid": 231428, "pts": [{"p": "rc", "c": ""}, {"p": "qc", "c": ""}, {"p": "qb", "c": ""}, {"p": "sd", "c": ""}], "v": 0, "ok_count": 0, "change_count": 0, "bad_count": 1, "error_count": 0, "created": 1561962540}, {"id": 1747041, "st": 1, "ty": 3, "nu": 18, "username": "\u90b1\u542f\u822a2022", "userid": 1326288, "pts": [{"p": "rc", "c": ""}, {"p": "qc", "c": ""}, {"p": "qb", "c": ""}, {"p": "sd", "c": ""}, {"p": "pb", "c": ""}, {"p": "rf", "c": ""}, {"p": "rg", "c": ""}, {"p": "rb", "c": ""}, {"p": "sb", "c": ""}, {"p": "ra", "c": ""}], "v": 0, "ok_count": 0, "change_count": 0, "bad_count": 1, "error_count": 0, "created": 1651672013}, {"id": 2579292, "st": 1, "ty": 3, "nu": 22, "username": "\u674e\u9e3f\u54f22015", "userid": 1313802, "pts": [{"p": "qb", "c": ""}, {"p": "rc", "c": ""}, {"p": "rb", "c": ""}, {"p": "pb", "c": ""}, {"p": "qc", "c": ""}, {"p": "rf", "c": ""}, {"p": "sc", "c": ""}, {"p": "se", "c": ""}, {"p": "sb", "c": ""}, {"p": "sd", "c": ""}, {"p": "rg", "c": ""}, {"p": "qa", "c": ""}, {"p": "sg", "c": ""}, {"p": "ra", "c": ""}, {"p": "sf", "c": ""}, {"p": "sa", "c": ""}], "v": 0, "ok_count": 0, "change_count": 0, "bad_count": 1, "error_count": 0, "created": 1739252313}, {"id": 2764571, "st": 1, "ty": 3, "nu": 23, "username": "Ericgolddd", "userid": 537488, "pts": [{"p": "rc", "c": ""}, {"p": "qc", "c": ""}, {"p": "qb", "c": ""}, {"p": "sd", "c": ""}, {"p": "pb", "c": ""}, {"p": "rf", "c": ""}, {"p": "sc", "c": ""}, {"p": "se", "c": ""}, {"p": "ra", "c": ""}, {"p": "sb", "c": ""}, {"p": "rb", "c": ""}, {"p": "pa", "c": ""}, {"p": "sg", "c": ""}, {"p": "rg", "c": ""}, {"p": "rh", "c": ""}, {"p": "oa", "c": ""}], "v": 0, "ok_count": 0, "change_count": 0, "bad_count": 1, "error_count": 0, "created": 1753541458}], "ans_count": 24, "andata": {"0": {"subs": [1, 22], "p": 0, "id": 0, "aids": [], "pt": "", "o": 0, "c": 0, "f": 0, "u": 0, "tip": ""}, "1": {"subs": [2, 8], "p": 0, "id": 1, "aids": [241749, 241968, 241970, 241969], "pt": "rc", "o": 1, "c": 1, "f": 1, "u": 0, "tip": ""}, "2": {"subs": [3, 20], "p": 1, "id": 2, "aids": [241749, 241970, 241969], "pt": "qc", "o": 1, "c": 1, "f": 1, "u": 0, "tip": ""}, "3": {"subs": [4, 14], "p": 2, "id": 3, "aids": [241749, 241970], "pt": "qb", "o": 1, "c": 1, "f": 0, "u": 0, "tip": ""}, "4": {"subs": [5], "p": 3, "id": 4, "aids": [241749], "pt": "pb", "o": 1, "c": 0, "f": 0, "u": 0, "tip": ""}, "5": {"subs": [6], "p": 4, "id": 5, "aids": [241749], "pt": "sd", "o": 1, "c": 0, "f": 0, "u": 0, "tip": ""}, "6": {"subs": [7], "p": 5, "id": 6, "aids": [241749], "pt": "pc", "o": 1, "c": 0, "f": 0, "u": 0, "tip": ""}, "7": {"subs": [], "p": 6, "id": 7, "aids": [241749], "pt": "ra", "o": 1, "c": 0, "f": 0, "u": 0, "tip": "\u606d\u559c\u7b54\u5bf9"}, "8": {"subs": [9], "p": 1, "id": 8, "aids": [241968], "pt": "rf", "o": 0, "c": 1, "f": 0, "u": 0, "tip": ""}, "9": {"subs": [10], "p": 8, "id": 9, "aids": [241968], "pt": "qc", "o": 0, "c": 1, "f": 0, "u": 0, "tip": ""}, "10": {"subs": [11], "p": 9, "id": 10, "aids": [241968], "pt": "se", "o": 0, "c": 1, "f": 0, "u": 0, "tip": ""}, "11": {"subs": [12], "p": 10, "id": 11, "aids": [241968], "pt": "sc", "o": 0, "c": 1, "f": 0, "u": 0, "tip": ""}, "12": {"subs": [13], "p": 11, "id": 12, "aids": [241968], "pt": "sd", "o": 0, "c": 1, "f": 0, "u": 0, "tip": ""}, "13": {"subs": [], "p": 12, "id": 13, "aids": [241968], "pt": "sg", "o": 0, "c": 1, "f": 0, "u": 0, "tip": ""}, "14": {"subs": [15], "p": 3, "id": 14, "aids": [241970], "pt": "sd", "o": 0, "c": 1, "f": 0, "u": 0, "tip": ""}, "15": {"subs": [16], "p": 14, "id": 15, "aids": [241970], "pt": "pb", "o": 0, "c": 1, "f": 0, "u": 0, "tip": ""}, "16": {"subs": [17], "p": 15, "id": 16, "aids": [241970], "pt": "rb", "o": 0, "c": 1, "f": 0, "u": 0, "tip": ""}, "17": {"subs": [18], "p": 16, "id": 17, "aids": [241970], "pt": "sb", "o": 0, "c": 1, "f": 0, "u": 0, "tip": ""}, "18": {"subs": [19], "p": 17, "id": 18, "aids": [241970], "pt": "sc", "o": 0, "c": 1, "f": 0, "u": 0, "tip": ""}, "19": {"subs": [], "p": 18, "id": 19, "aids": [241970], "pt": "ra", "o": 0, "c": 1, "f": 0, "u": 0, "tip": ""}, "20": {"subs": [21], "p": 2, "id": 20, "aids": [241969], "pt": "sd", "o": 0, "c": 0, "f": 1, "u": 0, "tip": ""}, "21": {"subs": [], "p": 20, "id": 21, "aids": [241969], "pt": "qb", "o": 0, "c": 0, "f": 1, "u": 0, "tip": ""}, "22": {"subs": [23], "p": 0, "id": 22, "aids": [241971], "pt": "qb", "o": 0, "c": 0, "f": 1, "u": 0, "tip": ""}, "23": {"subs": [24], "p": 22, "id": 23, "aids": [241971], "pt": "rc", "o": 0, "c": 0, "f": 1, "u": 0, "tip": ""}, "24": {"subs": [25], "p": 23, "id": 24, "aids": [241971], "pt": "rb", "o": 0, "c": 0, "f": 1, "u": 0, "tip": ""}, "25": {"subs": [26], "p": 24, "id": 25, "aids": [241971], "pt": "rf", "o": 0, "c": 0, "f": 1, "u": 0, "tip": ""}, "26": {"subs": [27], "p": 25, "id": 26, "aids": [241971], "pt": "sb", "o": 0, "c": 0, "f": 1, "u": 0, "tip": ""}, "27": {"subs": [28], "p": 26, "id": 27, "aids": [241971], "pt": "rg", "o": 0, "c": 0, "f": 1, "u": 0, "tip": ""}, "28": {"subs": [29], "p": 27, "id": 28, "aids": [241971], "pt": "sd", "o": 0, "c": 0, "f": 1, "u": 0, "tip": ""}, "29": {"subs": [30], "p": 28, "id": 29, "aids": [241971], "pt": "se", "o": 0, "c": 0, "f": 1, "u": 0, "tip": ""}, "30": {"subs": [31], "p": 29, "id": 30, "aids": [241971], "pt": "sc", "o": 0, "c": 0, "f": 1, "u": 0, "tip": ""}, "31": {"subs": [], "p": 30, "id": 31, "aids": [241971], "pt": "rh", "o": 0, "c": 0, "f": 1, "u": 0, "tip": ""}}, "disuse": 0, "sx": 12, "sy": 10, "pos_x1": 7, "pos_x2": 18, "pos_y1": 0, "pos_y2": 9, "ineb": false, "extendwidth": 0, "signs": [], "luozis": [], "isguess": false, "objtype": "timu", "ru": 2, "showai": false, "content": "amsTXFcRHRATXVcRHRATQVYRHRATQ1URHRATQlURHRATQ1YRHRATXVARHRATQlsRHRATXVURHRATQ1ARbBwRaBFZUhIdExFeUxIdExFCVBIdExFDVRIdExFCVRIdExFcUhIdExFBVRIdExFcUxIdExFdUxJsbg==", "ok_answers": "amsTQVARHRATQlARHRATQlERHRATQ1ERHRATQFcRHRATQ1ARHRATQVIRbG0=", "change_answers": "amsTQVARHRATQVURHRATQlARHRATQFYRHRATQFARHRATQFcRHRATQFQRbBwRaBFBUhIdExFCUhIdExFCUxIdExFAVRIdExFDUxIdExFBUxIdExFAUxIdExFAUhIdExFBUBJsbg==", "fail_answers": "amsTQVARHRATQlARHRATQFcRHRATQlERbBwRaBFCUxIdExFBUhIdExFBUxIdExFBVxIdExFAUxIdExFBVhIdExFAVRIdExFAVBIdExFAUhIdExFBWRJsbg==", "level": 440, "desc": "", "yes_count": 548, "no_count": 749, "pos": [], "attrtype": 0, "showrettip": false, "is_public": true, "inerror": false, "qshids": [], "myan": null, "hasbook": false, "hasspec": false, "myoper": {"mystar": false, "mytags": [], "tags": []}, "candisuseall": false, "userlevel": 0, "clicktime": 0, "xz": 0, "musthide": 0, "comments": [{"id": 371754, "dou": 0, "doustatus": 0, "douname": "", "username": "\u51af\u65fb\u704f", "userid": 208247, "headpath": "headicon_128.jpg", "updated": 1538825626, "showcontent": "\u5931\u9898\u4e86"}, {"id": 377102, "dou": 0, "doustatus": 0, "douname": "", "username": "\u5feb\u4e50\u5c0f\u7b1b\u5b50", "userid": 92390, "headpath": "head/2024/8/29/92390_27011_10_34.png", "updated": 1540696255, "showcontent": "\u9ed1\u68cb\u5355\u7c98\u4e0d\u597d\uff0c\u89c1\u7b54\u684814/15"}, {"id": 401217, "dou": 0, "doustatus": 0, "douname": "", "username": "Jessicajj", "userid": 110754, "headpath": "headicon_128.jpg", "updated": 1547554998, "showcontent": "\u54e6\uff1f"}, {"id": 401218, "dou": 0, "doustatus": 0, "douname": "", "username": "Jessicajj", "userid": 110754, "headpath": "headicon_128.jpg", "updated": 1547555030, "showcontent": "\u55ef\u55ef"}, {"id": 457305, "dou": 0, "doustatus": 0, "douname": "", "username": "\u6211\u7231\u5b66\u56f4\u68cb", "userid": 231428, "headpath": "head/2019/8/29/231428_67710_38_46.png", "updated": 1561962593, "showcontent": "\u6b64\u9898\u6709\u8bef\uff01\uff01\uff01"}, {"id": 908800, "dou": 0, "doustatus": 0, "douname": "", "username": "\u5f08\u4e4b\u5bb6\u8d75\u5a67", "userid": 794945, "headpath": "head/2020/6/10/794945_68790_49_5.png", "updated": 1602930628, "showcontent": "\u6211\u4e2a\u4eba\u8ba4\u4e3a\u53d8\u5316\u7b54\u684812\u662f\u6b63\u89e3\u2026\u2026\u767d\u68cb\u80af\u5b9a\u4f1a\u8fd9\u4e48\u9009\u62e9\u554a\uff0c\u5927\u591a\u4e86\u3002"}, {"id": 1334239, "dou": 0, "doustatus": 0, "douname": "", "username": "\u8a31\u65af\u7dad", "userid": 554010, "headpath": "head/2023/3/6/554010_20370_20_52.png", "updated": 1661750244, "showcontent": "<a href=\"/u/\u6211\u7231\u5b66\u56f4\u68cb/\" target=\"_blank\">@\u6211\u7231\u5b66\u56f4\u68cb</a> \u54ea\u91cc"}, {"id": 1662522, "dou": 0, "doustatus": 0, "douname": "", "username": "w_3522389819218", "userid": 553123, "headpath": "head/2024/8/19/553123_48757_40_19.png", "updated": 1699472195, "showcontent": "\u864e\u4f4f\uff01\uff01\uff01"}]}
