{"id": 180868, "qid": 180868, "publicid": 160790, "orgid": 0, "levelname": "6K+", "min_levelname": "", "max_levelname": "", "qtype": 1, "qtypename": "\u6b7b\u6d3b\u9898", "status": 2, "userid": 15812, "username": "dyz0", "hasdia": true, "dias": [], "attr_type": 0, "layoutnumber": 1, "issingle": true, "enable_answer": true, "sms_count": 0, "edit_count": 0, "islei": false, "leiid": 0, "taotaiid": 0, "bookinfos": [{"bookname": "\u3072\u3068\u76ee\u306e\u8a70\u7881 \u30ec\u30d9\u30eb\u30a2\u30c3\u30d7\u7de8", "bookid": 29616, "pinyin": "", "nodename": "PARTI \u6b7b\u306b", "bookurl": 29616}, {"bookname": "\u8d75\u6cbb\u52cb\u56f4\u68cb\u6b7b\u6d3b\u7cbe\u89e32", "bookid": 29281, "pinyin": "", "nodename": "\u7b2c2\u7ae0 \u6b7b\u68cb", "bookurl": 29281}], "specs": [], "taskresult": {"ok_nums": [18, 14, 23, 22, 48, 58, 95, 332, 696, 778, 1093, 887, 657, 490, 175, 89, 69, 50, 34, 21, 16, 22, 7, 16, 11, 14, 13, 6, 8, 9], "fail_nums": [18, 19, 24, 58, 104, 137, 251, 810, 1488, 1388, 1334, 778, 423, 238, 90, 49, 45, 26, 23, 16, 18, 16, 8, 15, 4, 8, 8, 0, 0, 5], "ok_total": 5771, "fail_total": 7401}, "xuandians": [], "xds": [], "options": [], "vote": 4.9, "name": "", "title": "", "c": "amsTQlIRHRATQlERHRATQlARHRATQ1cRHRATQlYRHRATXFYRHRATXVYRHRATXlcRHRATX1ARHRATWFARHRATWFERHRATXFIRbBwRaBFfUBIdExFfUxIdExFeUxIdExFdUhIdExFdVRIdExFcVRIdExFDUBIdExFDUxIdExFDUhJsbg==", "r": 2, "prepos": [["qa", "qb", "qc", "pd", "qe"], ["la", "lb", "mb"]], "xv": 9, "points": [], "lu": 19, "blackfirst": true, "is_share": true, "answers": [{"id": 985597, "st": 2, "ty": 1, "nu": 1, "username": "\u65b9\u5757A", "userid": 9316, "pts": [{"p": "ob", "c": ""}, {"p": "oc", "c": ""}, {"p": "na", "c": ""}], "v": 0, "ok_count": 52, "change_count": 0, "bad_count": 0, "error_count": 0, "created": 1579933784}, {"id": 3179545, "st": 1, "ty": 1, "nu": 9, "username": "wx_61244102193919", "userid": 2375176, "pts": [{"p": "ob", "c": ""}], "v": 0, "ok_count": 1, "change_count": 0, "bad_count": 0, "error_count": 0, "created": 1777370127}, {"id": 1035723, "st": 2, "ty": 1, "nu": 3, "username": "\u6d6e\u751f\u4e50\u900d\u9065", "userid": 723230, "pts": [{"p": "ob", "c": ""}, {"p": "oc", "c": ""}, {"p": "mc", "c": ""}, {"p": "nb", "c": ""}, {"p": "na", "c": ""}, {"p": "ma", "c": ""}, {"p": "oa", "c": ""}], "v": 0, "ok_count": 51, "change_count": 3, "bad_count": 0, "error_count": 0, "created": 1583227912}, {"id": 985598, "st": 2, "ty": 3, "nu": 2, "username": "\u65b9\u5757A", "userid": 9316, "pts": [{"p": "nb", "c": ""}, {"p": "na", "c": ""}, {"p": "ma", "c": ""}], "v": 0, "ok_count": 2, "change_count": 0, "bad_count": 53, "error_count": 0, "created": 1579933791}, {"id": 1075499, "st": 2, "ty": 3, "nu": 4, "username": "\u6797\u7426\u7fd46", "userid": 556935, "pts": [{"p": "ob", "c": ""}, {"p": "oc", "c": ""}, {"p": "nb", "c": ""}, {"p": "na", "c": ""}], "v": 0, "ok_count": 0, "change_count": 0, "bad_count": 53, "error_count": 0, "created": 1585811468}, {"id": 2115971, "st": 1, "ty": 3, "nu": 7, "username": "w_52445842195120", "userid": 1043159, "pts": [{"p": "ob", "c": ""}, {"p": "oc", "c": ""}, {"p": "mc", "c": ""}, {"p": "nb", "c": ""}, {"p": "na", "c": ""}, {"p": "ma", "c": ""}, {"p": "na", "c": ""}], "v": 0, "ok_count": 0, "change_count": 0, "bad_count": 1, "error_count": 0, "created": 1687051686}, {"id": 2183757, "st": 1, "ty": 3, "nu": 8, "username": "\u5e38\u6d3a\u7440", "userid": 1259832, "pts": [{"p": "oc", "c": ""}, {"p": "ob", "c": ""}, {"p": "na", "c": ""}, {"p": "nb", "c": ""}], "v": 0, "ok_count": 0, "change_count": 0, "bad_count": 1, "error_count": 0, "created": 1693568675}, {"id": 3220145, "st": 1, "ty": 3, "nu": 10, "username": "wx_521339354194211", "userid": 2504201, "pts": [{"p": "oc", "c": ""}], "v": 0, "ok_count": 0, "change_count": 0, "bad_count": 1, "error_count": 0, "created": 1779545504}], "ans_count": 8, "andata": {"0": {"subs": [1, 9], "p": 0, "id": 0, "aids": [], "pt": "", "o": 0, "c": 0, "f": 0, "u": 0, "tip": ""}, "1": {"subs": [2], "p": 0, "id": 1, "aids": [985597, 1035723, 1075499], "pt": "ob", "o": 1, "c": 0, "f": 1, "u": 0, "tip": ""}, "2": {"subs": [3, 4, 12], "p": 1, "id": 2, "aids": [985597, 1035723, 1075499], "pt": "oc", "o": 1, "c": 0, "f": 1, "u": 0, "tip": ""}, "3": {"subs": [], "p": 2, "id": 3, "aids": [985597], "pt": "na", "o": 1, "c": 0, "f": 0, "u": 0, "tip": ""}, "4": {"subs": [5], "p": 2, "id": 4, "aids": [1035723], "pt": "mc", "o": 1, "c": 0, "f": 0, "u": 0, "tip": ""}, "5": {"subs": [6], "p": 4, "id": 5, "aids": [1035723], "pt": "nb", "o": 1, "c": 0, "f": 0, "u": 0, "tip": ""}, "6": {"subs": [7], "p": 5, "id": 6, "aids": [1035723], "pt": "na", "o": 1, "c": 0, "f": 0, "u": 0, "tip": ""}, "7": {"subs": [8], "p": 6, "id": 7, "aids": [1035723], "pt": "ma", "o": 1, "c": 0, "f": 0, "u": 0, "tip": ""}, "8": {"subs": [], "p": 7, "id": 8, "aids": [1035723], "pt": "oa", "o": 1, "c": 0, "f": 0, "u": 0, "tip": ""}, "9": {"subs": [10], "p": 0, "id": 9, "aids": [985598], "pt": "nb", "o": 0, "c": 0, "f": 1, "u": 0, "tip": ""}, "10": {"subs": [11], "p": 9, "id": 10, "aids": [985598], "pt": "na", "o": 0, "c": 0, "f": 1, "u": 0, "tip": ""}, "11": {"subs": [], "p": 10, "id": 11, "aids": [985598], "pt": "ma", "o": 0, "c": 0, "f": 1, "u": 0, "tip": ""}, "12": {"subs": [13], "p": 2, "id": 12, "aids": [1075499], "pt": "nb", "o": 0, "c": 0, "f": 1, "u": 0, "tip": ""}, "13": {"subs": [], "p": 12, "id": 13, "aids": [1075499], "pt": "na", "o": 0, "c": 0, "f": 1, "u": 0, "tip": ""}}, "disuse": 2, "sx": 11, "sy": 7, "pos_x1": 8, "pos_x2": 18, "pos_y1": 0, "pos_y2": 6, "ineb": false, "extendwidth": 0, "signs": [], "luozis": [], "isguess": false, "objtype": "timu", "ru": 1, "showai": false, "content": "amsTXlEQHRATX1YQHRATQ1cQHRATQlYQHRATXVMQHRATQ1EQHRATQ1AQHRATWVAQHRATWVEQHRATXFcQHRATQ1MQHRATXVcQbBwRaRBfUxIdEhBCUxIdEhBdVRIdEhBCUBIdEhBcUhIdEhBcVRIdEhBeUBIdEhBCUhIdEhBeUxJsbw==", "ok_answers": "amsTXVAQHRATXVEQHRATXFMQbBwRaRBdUxIdEhBdUhIdEhBfUhIdEhBcUxIdEhBcUBIdEhBfUBIdEhBdUBJsbw==", "change_answers": "am0=", "fail_answers": "amsTXFAQHRATXFMQHRATX1MQbBwRaRBdUxIdEhBdUhIdEhBcUxIdEhBcUBJsbw==", "level": 134, "desc": "", "yes_count": 5771, "no_count": 7401, "pos": [], "attrtype": 0, "showrettip": false, "is_public": true, "inerror": false, "qshids": [], "myan": null, "hasbook": false, "hasspec": false, "myoper": {"mystar": false, "mytags": [], "tags": []}, "candisuseall": false, "userlevel": 0, "clicktime": 500, "xz": 0, "musthide": 0, "comments": [{"id": 896745, "dou": 0, "doustatus": 0, "douname": "", "username": "wenads", "userid": 561734, "headpath": "headicon_128.jpg", "updated": 1601293336, "showcontent": "\u9019\u984c\u6bd4\u8f03\u5bb9\u6613"}, {"id": 1085550, "dou": 0, "doustatus": 0, "douname": "", "username": "zhx100", "userid": 687408, "headpath": "headicon_128.jpg", "updated": 1630822754, "showcontent": "\u5bf9\u5bf9\u5bf9"}, {"id": 1186905, "dou": 0, "doustatus": 0, "douname": "", "username": "w_31592953191010", "userid": 1310824, "headpath": "head/2022/2/19/1310824_33154_18_27.png", "updated": 1647774514, "showcontent": "\u505a\u5f2f\u5934"}, {"id": 1252638, "dou": 0, "doustatus": 0, "douname": "", "username": "\u5434\u5b87\u6db5Y", "userid": 984015, "headpath": "head/2022/8/4/984015_64947_13_54.png", "updated": 1654578259, "showcontent": "\u5047\u53cc\u6d3b"}, {"id": 1347585, "dou": 0, "doustatus": 0, "douname": "", "username": "\u66fe\u5b87\u5353", "userid": 1511496, "headpath": "headicon_128.jpg", "updated": 1663322696, "showcontent": "\u8c01\u60f3\u6253\u52ab\u5462\uff1f\u4e00"}, {"id": 1360307, "dou": 0, "doustatus": 0, "douname": "", "username": "\u6e05\u4e00\u67ef\u4e60\u58a8", "userid": 470900, "headpath": "headicon_128.jpg", "updated": 1664880462, "showcontent": "\u6211\uff01"}, {"id": 1454292, "dou": 0, "doustatus": 0, "douname": "", "username": "wx_5362833319629", "userid": 1377277, "headpath": "headicon_128.jpg", "updated": 1673878243, "showcontent": "\u4e0d\u884c\u6253\u8f93\u4e86\u600e\u4e48\u529e"}, {"id": 1527284, "dou": 0, "doustatus": 0, "douname": "", "username": "wx_56454312194811", "userid": 1060086, "headpath": "headicon_128.jpg", "updated": 1681728063, "showcontent": "\u51c9\u62cc"}, {"id": 1595527, "dou": 0, "doustatus": 0, "douname": "", "username": "wx_52685956191521", "userid": 1488926, "headpath": "headicon_128.jpg", "updated": 1691315888, "showcontent": "\u70b9\u5f2f\u4e09"}, {"id": 1606828, "dou": 0, "doustatus": 0, "douname": "", "username": "wx_2043818419391", "userid": 1030855, "headpath": "headicon_128.jpg", "updated": 1692250949, "showcontent": "\u7b80\u5355"}, {"id": 1749856, "dou": 0, "doustatus": 0, "douname": "", "username": "wx_4771936192314", "userid": 1639285, "headpath": "headicon_128.jpg", "updated": 1709638237, "showcontent": "\u714e\u86cb\uff01\uff01\uff01"}, {"id": 2101163, "dou": 0, "doustatus": 0, "douname": "", "username": "\u53f6\u5955\u607ahq", "userid": 2257968, "headpath": "headicon_128.jpg", "updated": 1746927838, "showcontent": "\u51c9\u62cc"}, {"id": 2222968, "dou": 0, "doustatus": 0, "douname": "", "username": "\u5353\u8d8a\u4e0d\u51e1\u7428", "userid": 1727214, "headpath": "userhead/2.jpg", "updated": 1755345257, "showcontent": "\u6700\u597d\u5403"}, {"id": 2229103, "dou": 0, "doustatus": 0, "douname": "", "username": "wx_1088498319158", "userid": 1828366, "headpath": "headicon_128.jpg", "updated": 1755678574, "showcontent": "\u592a\u96be\u4e86\ud83d\ude2b"}, {"id": 2317110, "dou": 0, "doustatus": 0, "douname": "", "username": "\u725b\u725b666666", "userid": 1950184, "headpath": "head/2025/4/1/1950184_53476_58_9.png", "updated": 1761799450, "showcontent": "\u53c8\u70b9\u9519\u4e86\u3002"}, {"id": 2356926, "dou": 0, "doustatus": 0, "douname": "", "username": "wx_6895594192322", "userid": 1845403, "headpath": "headicon_128.jpg", "updated": 1764844152, "showcontent": "\u7b80\u5355\u7684\u5f88\u3002"}, {"id": 2383362, "dou": 0, "doustatus": 0, "douname": "", "username": "\u8096\u4f73\u94ed", "userid": 1982704, "headpath": "userhead/3.jpg", "updated": 1766889706, "showcontent": "\u5e94\u8be5\u8c03\u52307k\u5427\u3002"}, {"id": 2498731, "dou": 0, "doustatus": 0, "douname": "", "username": "\u5317\u4eac\u82f1\u96c4", "userid": 2338087, "headpath": "headicon_128.jpg", "updated": 1773826916, "showcontent": "\u7b80\u5355\u7684\u8981\u6b7b\u3002"}, {"id": 2498735, "dou": 0, "doustatus": 0, "douname": "", "username": "\u5317\u4eac\u82f1\u96c4", "userid": 2338087, "headpath": "headicon_128.jpg", "updated": 1773826966, "showcontent": "10000000"}, {"id": 2536609, "dou": 0, "doustatus": 0, "douname": "", "username": "\u590f\u535a\u6587123", "userid": 2377209, "headpath": "headicon_128.jpg", "updated": 1776249874, "showcontent": "\u4f60\u90a3\u4e2a\u4e00\u4e09\u3002"}, {"id": 2549245, "dou": 0, "doustatus": 0, "douname": "", "username": "wx_51109805819404", "userid": 2161955, "headpath": "headicon_128.jpg", "updated": 1776951871, "showcontent": "\u597d\u5566"}]}
