{"id": 81173, "qid": 81173, "publicid": 81173, "orgid": 0, "levelname": "10K+", "min_levelname": "", "max_levelname": "", "qtype": 2, "qtypename": "\u624b\u7b4b\u9898", "status": 2, "userid": 4296, "username": "lst931207", "hasdia": true, "dias": [], "attr_type": 0, "layoutnumber": 1, "issingle": true, "enable_answer": true, "sms_count": 1, "edit_count": 1, "islei": false, "leiid": 0, "taotaiid": 0, "bookinfos": [], "specs": [], "taskresult": {"ok_nums": [176, 299, 874, 1747, 1860, 1789, 1298, 1294, 529, 325, 260, 208, 154, 105, 70, 60, 55, 37, 59, 23, 20, 25, 19, 18, 5, 10, 18, 2, 2, 11], "fail_nums": [442, 466, 1812, 2261, 1696, 1250, 588, 323, 150, 75, 66, 54, 35, 30, 28, 16, 20, 11, 7, 11, 6, 4, 4, 3, 2, 3, 1, 0, 2, 0], "ok_total": 11352, "fail_total": 9366}, "xuandians": [], "xds": [], "options": [], "vote": 4.8, "name": "", "title": "", "c": "amsTQ1YRHRATQ1URHRATXVYRHRATWFYRHRATWFcRHRATX1ARHRATXlARHRATXVARHRATXFcRHRATQ1cRbBwRaBFCUhIdExFcUhIdExFcUxIdExFdUxIdExFcVBIdExFcVhIdExFdVRIdExFeVRIdExFfVRIdExFeVBIdExFeWRIdExFYUhIdExFYUxJsbg==", "r": 2, "prepos": [["pe", "pf", "ne", "ke", "kd"], ["qc", "oc", "ob"]], "xv": 9, "points": [], "lu": 19, "blackfirst": true, "is_share": true, "answers": [{"id": 458176, "st": 2, "ty": 1, "nu": 1, "username": "lst931207", "userid": 4339, "pts": [{"p": "mf", "c": ""}, {"p": "nf", "c": ""}, {"p": "le", "c": ""}, {"p": "ne", "c": ""}, {"p": "ng", "c": ""}, {"p": "of", "c": ""}, {"p": "oh", "c": ""}], "v": 0, "ok_count": 4, "change_count": 0, "bad_count": 0, "error_count": 0, "created": 1484801012}, {"id": 2336711, "st": 1, "ty": 1, "nu": 9, "username": "\u96c1\u884c\u6797\u5bb6\u5b89", "userid": 1901193, "pts": [{"p": "of", "c": ""}, {"p": "nf", "c": ""}, {"p": "mf", "c": ""}, {"p": "le", "c": ""}, {"p": "lf", "c": ""}, {"p": "ng", "c": ""}, {"p": "mg", "c": ""}, {"p": "lg", "c": ""}, {"p": "kg", "c": ""}, {"p": "lh", "c": ""}, {"p": "kh", "c": ""}, {"p": "nh", "c": ""}], "v": 0, "ok_count": 1, "change_count": 0, "bad_count": 0, "error_count": 1, "created": 1713862982}, {"id": 2336714, "st": 1, "ty": 1, "nu": 10, "username": "\u96c1\u884c\u6797\u5bb6\u5b89", "userid": 1901193, "pts": [{"p": "nf", "c": ""}, {"p": "of", "c": ""}, {"p": "mf", "c": ""}, {"p": "le", "c": ""}, {"p": "lf", "c": ""}], "v": 0, "ok_count": 2, "change_count": 0, "bad_count": 0, "error_count": 0, "created": 1713863206}, {"id": 2382777, "st": 1, "ty": 1, "nu": 11, "username": "\u5218\u8fd0\u4ead", "userid": 64850, "pts": [{"p": "nf", "c": ""}, {"p": "mf", "c": ""}, {"p": "mg", "c": ""}, {"p": "lg", "c": ""}, {"p": "of", "c": ""}, {"p": "lh", "c": ""}, {"p": "lf", "c": ""}, {"p": "nh", "c": ""}, {"p": "ng", "c": ""}, {"p": "kf", "c": ""}, {"p": "le", "c": ""}], "v": 0, "ok_count": 1, "change_count": 0, "bad_count": 0, "error_count": 0, "created": 1718967127}, {"id": 3163350, "st": 1, "ty": 3, "nu": 13, "username": "\u4f55\u5fc3\u8fdc\u540c\u5b66", "userid": 2263023, "pts": [{"p": "mf", "c": ""}, {"p": "nf", "c": ""}, {"p": "le", "c": ""}, {"p": "ne", "c": ""}, {"p": "ng", "c": ""}, {"p": "of", "c": ""}, {"p": "oh", "c": ""}, {"p": "pg", "c": ""}], "v": 0, "ok_count": 0, "change_count": 0, "bad_count": 1, "error_count": 0, "created": 1776403340}, {"id": 2145540, "st": 1, "ty": 3, "nu": 5, "username": "\u6797\u5c0f\u704f", "userid": 1463914, "pts": [{"p": "nf", "c": ""}, {"p": "mf", "c": ""}], "v": 0, "ok_count": 0, "change_count": 0, "bad_count": 2, "error_count": 0, "created": 1690337351}, {"id": 2155502, "st": 1, "ty": 3, "nu": 7, "username": "wx_20698348192411", "userid": 1510994, "pts": [{"p": "nf", "c": ""}], "v": 0, "ok_count": 0, "change_count": 0, "bad_count": 1, "error_count": 0, "created": 1691151977}, {"id": 3159560, "st": 1, "ty": 3, "nu": 12, "username": "x_271037628194315", "userid": 2070509, "pts": [{"p": "mf", "c": ""}, {"p": "nf", "c": ""}, {"p": "of", "c": ""}, {"p": "mg", "c": ""}, {"p": "lf", "c": ""}, {"p": "ne", "c": ""}], "v": 0, "ok_count": 0, "change_count": 0, "bad_count": 1, "error_count": 0, "created": 1776170242}], "ans_count": 8, "andata": {"0": {"subs": [1], "p": 0, "id": 0, "aids": [], "pt": "", "o": 0, "c": 0, "f": 0, "u": 0, "tip": ""}, "1": {"subs": [2], "p": 0, "id": 1, "aids": [458176], "pt": "mf", "o": 1, "c": 0, "f": 0, "u": 0, "tip": ""}, "2": {"subs": [3], "p": 1, "id": 2, "aids": [458176], "pt": "nf", "o": 1, "c": 0, "f": 0, "u": 0, "tip": ""}, "3": {"subs": [4], "p": 2, "id": 3, "aids": [458176], "pt": "le", "o": 1, "c": 0, "f": 0, "u": 0, "tip": ""}, "4": {"subs": [5], "p": 3, "id": 4, "aids": [458176], "pt": "ne", "o": 1, "c": 0, "f": 0, "u": 0, "tip": ""}, "5": {"subs": [6], "p": 4, "id": 5, "aids": [458176], "pt": "ng", "o": 1, "c": 0, "f": 0, "u": 0, "tip": ""}, "6": {"subs": [7], "p": 5, "id": 6, "aids": [458176], "pt": "of", "o": 1, "c": 0, "f": 0, "u": 0, "tip": ""}, "7": {"subs": [], "p": 6, "id": 7, "aids": [458176], "pt": "oh", "o": 1, "c": 0, "f": 0, "u": 0, "tip": ""}}, "disuse": 4, "sx": 12, "sy": 11, "pos_x1": 7, "pos_x2": 18, "pos_y1": 0, "pos_y2": 10, "ineb": false, "extendwidth": 1, "signs": [], "luozis": [], "isguess": false, "objtype": "timu", "ru": 1, "showai": false, "content": "amsTWVYQHRATX1EQHRATXlEQHRATQlcQHRATQlYQHRATXFcQHRATQlQQHRATXFEQHRATXVYQHRATWVcQbBwRaRBfWRIdEhBdVBIdEhBdUhIdEhBcUxIdEhBfVRIdEhBdVhIdEhBZUxIdEhBdUxIdEhBfVBIdEhBcVRIdEhBeVRIdEhBDUhIdEhBZUhJsbw==", "ok_answers": "amsTX1QQHRATXFQQHRATXlcQHRATXFcQHRATXFUQHRATXVQQHRATXVoQbG0=", "change_answers": "am0=", "fail_answers": "am0=", "level": 16, "desc": "", "yes_count": 11352, "no_count": 9366, "pos": [], "attrtype": 0, "showrettip": false, "is_public": true, "inerror": false, "qshids": [], "myan": null, "hasbook": false, "hasspec": false, "myoper": {"mystar": false, "mytags": [], "tags": []}, "candisuseall": false, "userlevel": 0, "clicktime": 500, "xz": 0, "musthide": 0, "comments": [{"id": 754755, "dou": 0, "doustatus": 0, "douname": "", "username": "clt", "userid": 673051, "headpath": "head/2020/5/19/673051_66242_57_6.png", "updated": 1589684094, "showcontent": "BAD IDEA"}, {"id": 876826, "dou": 0, "doustatus": 0, "douname": "", "username": "wx_1025169519813", "userid": 625423, "headpath": "headicon_128.jpg", "updated": 1598404640, "showcontent": "\u6eda\u6253\u5305\u6536"}, {"id": 1059220, "dou": 0, "doustatus": 0, "douname": "", "username": "wx_193605321947", "userid": 890006, "headpath": "head/2021/7/26/890006_59289_25_43.png", "updated": 1627311280, "showcontent": "\u55ef"}, {"id": 1262000, "dou": 0, "doustatus": 0, "douname": "", "username": "\u5218\u5f18\u5c79", "userid": 1118325, "headpath": "head/2023/2/1/1118325_2503_12_38.png", "updated": 1655601398, "showcontent": "\u5f81"}, {"id": 1417692, "dou": 0, "doustatus": 0, "douname": "", "username": "dscj\u8212\u6893\u8f69", "userid": 1330894, "headpath": "headicon_128.jpg", "updated": 1671331446, "showcontent": "\u8fd9"}, {"id": 2116990, "dou": 0, "doustatus": 0, "douname": "", "username": "\u9646\u79b9\u679c", "userid": 2231144, "headpath": "head/2025/7/22/2116209_8508_40_55.png", "updated": 1748321805, "showcontent": "\u5403"}, {"id": 2350466, "dou": 0, "doustatus": 0, "douname": "", "username": "wx_461143557193918", "userid": 2232689, "headpath": "headicon_128.jpg", "updated": 1764374976, "showcontent": "\u4e0d\u96be"}, {"id": 2355207, "dou": 0, "doustatus": 0, "douname": "", "username": "wx_58118675919229", "userid": 2295487, "headpath": "headicon_128.jpg", "updated": 1764683731, "showcontent": "\u6eda\u6253\u5305\u6536\u52a0\u7565\u9633\u5934"}, {"id": 2504954, "dou": 0, "doustatus": 0, "douname": "", "username": "\u5510\u7478\u8d3a", "userid": 2156724, "headpath": "headicon_128.jpg", "updated": 1774257456, "showcontent": "\u7b80\u5355"}, {"id": 2557809, "dou": 0, "doustatus": 0, "douname": "", "username": "SNG\u9a6c\u4f9d\u73ca", "userid": 2496004, "headpath": "headicon_128.jpg", "updated": 1777458109, "showcontent": "\u9519\u274c"}]}
